Metadata-Version: 2.1
Name: schedpack
Version: 1.1.1
Summary: Package for scheduling activities that last some time
Home-page: https://github.com/Borisoid/schedpack
Author: borisoid
License: MIT
Keywords: schedule,lasting,cron
Platform: UNKNOWN
Classifier: Development Status :: 4 - Beta
Classifier: Intended Audience :: Developers
Classifier: Topic :: Software Development :: Libraries :: Python Modules
Classifier: License :: OSI Approved :: MIT License
Classifier: Programming Language :: Python :: 3
Classifier: Programming Language :: Python :: 3.8
